e2b_agent/__init__.py
e2b_agent/agent.py
e2b_agent/dependencies.py
e2b_agent/models.py
e2b_agent/routers/actions.py
e2b_agent/routers/state.py
e2b_agent/server.py
e2b_agent/start.py
kuba_test_e2b_agent-0.0.1.dist-info/WHEEL
kuba_test_e2b_agent-0.0.1.dist-info/entry_points.txt
kuba_test_e2b_agent-0.0.1.dist-info/METADATA
kuba_test_e2b_agent-0.0.1.dist-info/RECORD
