Metadata-Version: 2.1
Name: kuba-test-e2b-agent
Version: 0.0.1
Summary: API for interacting with Agent
License: MIT
Author: e2b
Author-email: hello@e2b.dev
Requires-Python: >=3.10,<4.0
Classifier: License :: OSI Approved :: MIT License
Classifier: Programming Language :: Python :: 3
Classifier: Programming Language :: Python :: 3.10
Classifier: Programming Language :: Python :: 3.11
Requires-Dist: fastapi (>=0.100.0,<0.101.0)
Requires-Dist: fastapi-code-generator (>=0.4.2,<0.5.0)
Requires-Dist: uvicorn[standard] (>=0.22.0,<0.23.0)
